{
    "fluentMethods": true,
    "relationships": [
        {
            "relationshipType": "many-to-one",
            "relationshipName": "tipo",
            "otherEntityName": "tipo",
            "otherEntityField": "nombre"
        },
        {
            "relationshipType": "many-to-one",
            "relationshipName": "beneficio",
            "otherEntityName": "beneficio",
            "otherEntityField": "nombre"
        }
    ],
    "fields": [
        {
            "fieldName": "kg",
            "fieldType": "Integer",
            "fieldValidateRules": [
                "required",
                "min"
            ],
            "fieldValidateRulesMin": 0
        },
        {
            "fieldName": "fecha",
            "fieldType": "ZonedDateTime",
            "fieldValidateRules": [
                "required"
            ]
        }
    ],
    "changelogDate": "20170215043053",
    "entityTableName": "entrada",
    "dto": "mapstruct",
    "pagination": "pager",
    "service": "serviceClass",
    "angularJSSuffix": "ang"
}